{"id":320671,"title":"fgjcdmx investiga a exfuncionarios por corrupción: ernestina godoy","summary":"la titular de la fiscalía general de justicia de la ciudad de méxico (fgjcdmx), ernestina godoy, se reunió virtualmente con diputados locales, a quienes aseguró que la institución a su cargo está investigando a funcionarios de la administración pasada, por actos de corrupción que calificó como los más grandes registrados en la capital del país....","content":"la titular de la fiscalía general de justicia de la ciudad de méxico (fgjcdmx), ernestina godoy, se reunió virtualmente con diputados locales, a quienes aseguró que la institución a su cargo está investigando a funcionarios de la administración pasada, por actos de corrupción que calificó como los más grandes registrados en la capital del país.“investigamos y procesamos hechos graves de corrupción de funcionarios de la anterior administración que rebasan los límites de la responsabilidad individual; hemos reconstruido mapas completos de operaciones financieras y administrativas, públicas y privadas, de varios exsecretarios, subsecretarios, directores generales, exlegisladores, exjefes delegaciones, que develan la implantación y operación de una maquinaria para el desvío sistemático de miles de millones de recursos de la hacienda pública de la cdmx, al más alto nivel y con participación directa de altos funcionarios, se instauró un sistema minuciosamente planeado para extraer grandes cantidades de recursos públicos. les puedo asegurar que estamos frente a los hechos de corrupción más grandes de que se tenga registro en la cdmx y uno de los más relevantes en el país. tenemos evidencias que soportan cada una de estas afirmaciones”, informó ernestina godoy, fiscal general de justicia de la cdmx.dijo que conforme avancen las investigaciones habrá más detenidos y, en cuanto la ley lo permita, dará a conocer más detalles de las mismas.al momento, apuntó, son 23 carpetas de investigación, que involucran a 35 funcionarios públicos en el desvío de aproximadamente mil 588 millones de pesos, 12 de los involucrados ya han sido llevados ante tribunales y se encuentran en proceso, aseguró.la fiscal detalló, por otro lado, que, gracias a la coordinación con distintas instituciones, locales y federales, 219 objetivos criminales relevantes fueron detenidos y puestos a disposición de jueces, durante el 2020.sobre el tema y a pregunta expresa godoy admitió que hay operaciones del crimen organizado en la ciudad, pero aseguró que se está investigando.“sí, tenemos ubicados, lo hemos comentado, a todos los grupos criminales, sus niveles de influencia, sus relaciones con otras expresiones criminales organizadas incluso externas a la ciudad; el programa de persecución penal considera la existencia de ellos y las cadenas criminales que se articulan en torno a ellos; no, no negamos, lo he dicho, no negamos la existencia de bandas criminales, pero tampoco ni los protegemos ni los encubrimos”, agregó godoy.finalmente, la funcionaria admitió que la incidencia del delito de violación no ha bajado y de hecho ha incrementado en la ciudad de méxico.en 2018 hubo mil 397 denuncias, mientras en 2020 fueron mil 505 denuncias por este ilícito, un incremento de 7.7%.","estado":9,"municipio":0,"asentamiento":0,"cp":0,"idPostalCode":0}